qdna/__init__.py
qdna/graph.py
qdna/quantum_info.py
qdna/ansatz/__init__.py
qdna/ansatz/qcnn.py
qdna/compression/__init__.py
qdna/compression/compressor.py
qdna/compression/schmidt.py
qdna/embedding/__init__.py
qdna/embedding/ae_feature_map.py
qdna/embedding/iqp_feature_map.py
qdna/embedding/nqe_ae_feature_map.py
qdna/embedding/nqe_base.py
qdna/embedding/nqe_iqp_feature_map.py
qdna/embedding/nqe_z_feature_map.py
qdna/embedding/nqe_zz_feature_map.py
test/__init__.py
test/test_graph.py
test/compression/__init__.py
test/compression/test_schmidt.py
test/embedding/__init__.py
test/embedding/test_ae_feature_map.py
test/embedding/util/__init__.py
test/embedding/util/test_ucr.py
qdna_lib-0.0.2.dist-info/LICENSE
qdna_lib-0.0.2.dist-info/METADATA
qdna_lib-0.0.2.dist-info/WHEEL
qdna_lib-0.0.2.dist-info/top_level.txt
qdna_lib-0.0.2.dist-info/RECORD
