Metadata-Version: 2.1
Name: qdna-lib
Version: 0.0.2
Summary: A quantum computing library for data science and artificial intelligence
Home-page: https://github.com/qDNA-yonsei/qdna-lib
Author: qdna team
Author-email: ifa@yonsei.ac.kr
Classifier: Programming Language :: Python :: 3
Classifier: Operating System :: OS Independent
Requires-Python: >=3.8
License-File: LICENSE
Requires-Dist: qiskit >=1.0.0
Requires-Dist: qiskit-machine-learning >=0.7.2
Requires-Dist: qiskit-aer >=0.13.3
Requires-Dist: qiskit-algorithms >=0.3.0
Requires-Dist: qclib >=0.1.12
Requires-Dist: dwave-ocean-sdk >=6.9.0
Requires-Dist: torch
Requires-Dist: networkx
